spacy_wordnet/__init__.py
spacy_wordnet/__utils__.py
spacy_wordnet/wordnet_annotator.py
spacy_wordnet/wordnet_domains.py
spacy_wordnet/data/wordnet_domains.txt
spacy_wordnet-0.1.0.dist-info/AUTHORS.rst
spacy_wordnet-0.1.0.dist-info/LICENSE.txt
spacy_wordnet-0.1.0.dist-info/METADATA
spacy_wordnet-0.1.0.dist-info/WHEEL
spacy_wordnet-0.1.0.dist-info/top_level.txt
spacy_wordnet-0.1.0.dist-info/RECORD
