Metadata-Version: 2.1
Name: spacy-wordnet
Version: 0.1.0
Summary: Add a short description here!
Home-page: https://github.com/recognai/spacy-wordnet
Author: Francisco Aranda
Author-email: francisco@recogn.ai
License: mit
Platform: any
Classifier: Development Status :: 4 - Beta
Classifier: Programming Language :: Python
License-File: LICENSE.txt
License-File: AUTHORS.rst
Requires-Dist: nltk (<3.6,>=3.3)
Requires-Dist: spacy (>=2)
Provides-Extra: testing
Requires-Dist: pytest ; extra == 'testing'
Requires-Dist: pytest-cov ; extra == 'testing'
